<?xml version="1.0" encoding="utf-8" ?>
<dwsync>
<file name="sweetalert2.all.js" server="69.175.104.242//" local="132244609210862004" remote="132212676600000000" Dst="0" />
<file name="sweetalert2.all.min.js" server="69.175.104.242//" local="132244609212840862" remote="132212676600000000" Dst="0" />
<file name="sweetalert2.css" server="69.175.104.242//" local="132244609213090923" remote="132212676600000000" Dst="0" />
<file name="sweetalert2.js" server="69.175.104.242//" local="132244609218407698" remote="132212676600000000" Dst="0" />
<file name="sweetalert2.min.css" server="69.175.104.242//" local="132244609218477631" remote="132212676600000000" Dst="0" />
<file name="sweetalert2.min.js" server="69.175.104.242//" local="132244609219289174" remote="132212676600000000" Dst="0" />
<file name="sweetalert2.all.js" server="alcaldialaunion.gob.sv//" local="132372423829141932" remote="132271495200000000" Dst="0" />
<file name="sweetalert2.all.min.js" server="alcaldialaunion.gob.sv//" local="132372423829749957" remote="132271495200000000" Dst="0" />
<file name="sweetalert2.css" server="alcaldialaunion.gob.sv//" local="132372423831520141" remote="132271495200000000" Dst="0" />
<file name="sweetalert2.js" server="alcaldialaunion.gob.sv//" local="132372423836455231" remote="132271495200000000" Dst="0" />
<file name="sweetalert2.min.css" server="alcaldialaunion.gob.sv//" local="132372423835540945" remote="132271495200000000" Dst="0" />
<file name="sweetalert2.min.js" server="alcaldialaunion.gob.sv//" local="132372423836881549" remote="132271495200000000" Dst="0" />
</dwsync>