<?xml version="1.0" encoding="utf-8" ?>
<dwsync>
<file name="af.js" server="69.175.104.242//" local="132244608900340616" remote="132233482200000000" Dst="0" />
<file name="ar.js" server="69.175.104.242//" local="132244608900840348" remote="132233482200000000" Dst="0" />
<file name="az.js" server="69.175.104.242//" local="132244608902089614" remote="132233482200000000" Dst="0" />
<file name="bg.js" server="69.175.104.242//" local="132244608904708121" remote="132233482200000000" Dst="0" />
<file name="bn.js" server="69.175.104.242//" local="132244608905517673" remote="132233482200000000" Dst="0" />
<file name="bs.js" server="69.175.104.242//" local="132244608907696423" remote="132233482200000000" Dst="0" />
<file name="build.txt" server="69.175.104.242//" local="132244608909935139" remote="132233482200000000" Dst="0" />
<file name="ca.js" server="69.175.104.242//" local="132244608910834611" remote="132233482200000000" Dst="0" />
<file name="cs.js" server="69.175.104.242//" local="132244608913110534" remote="132233482200000000" Dst="0" />
<file name="da.js" server="69.175.104.242//" local="132244608914679620" remote="132233482200000000" Dst="0" />
<file name="de.js" server="69.175.104.242//" local="132244608915669042" remote="132233482200000000" Dst="0" />
<file name="dsb.js" server="69.175.104.242//" local="132244608917827817" remote="132233482200000000" Dst="0" />
<file name="el.js" server="69.175.104.242//" local="132244608919986602" remote="132233482200000000" Dst="0" />
<file name="en.js" server="69.175.104.242//" local="132244608920756143" remote="132233482200000000" Dst="0" />
<file name="es.js" server="69.175.104.242//" local="132244608922525138" remote="132233482200000000" Dst="0" />
<file name="et.js" server="69.175.104.242//" local="132244608924314115" remote="132233482200000000" Dst="0" />
<file name="eu.js" server="69.175.104.242//" local="132244608925522733" remote="132233482200000000" Dst="0" />
<file name="fa.js" server="69.175.104.242//" local="132244608927891430" remote="132233482200000000" Dst="0" />
<file name="fi.js" server="69.175.104.242//" local="132244608928947000" remote="132233482200000000" Dst="0" />
<file name="fr.js" server="69.175.104.242//" local="132244608930725984" remote="132233482200000000" Dst="0" />
<file name="gl.js" server="69.175.104.242//" local="132244608932614906" remote="132233482200000000" Dst="0" />
<file name="he.js" server="69.175.104.242//" local="132244608933674295" remote="132233482200000000" Dst="0" />
<file name="hi.js" server="69.175.104.242//" local="132244608935733121" remote="132233482200000000" Dst="0" />
<file name="hr.js" server="69.175.104.242//" local="132244608938005901" remote="132233482200000000" Dst="0" />
<file name="hsb.js" server="69.175.104.242//" local="132244608938995354" remote="132233482200000000" Dst="0" />
<file name="hu.js" server="69.175.104.242//" local="132244608940654396" remote="132233482200000000" Dst="0" />
<file name="hy.js" server="69.175.104.242//" local="132244608944192447" remote="132233482200000000" Dst="0" />
<file name="id.js" server="69.175.104.242//" local="132244608945651671" remote="132233482200000000" Dst="0" />
<file name="is.js" server="69.175.104.242//" local="132244608947500691" remote="132233482200000000" Dst="0" />
<file name="it.js" server="69.175.104.242//" local="132244608948480138" remote="132233482200000000" Dst="0" />
<file name="ja.js" server="69.175.104.242//" local="132244608950169204" remote="132233482200000000" Dst="0" />
<file name="ka.js" server="69.175.104.242//" local="132244608951938248" remote="132233482200000000" Dst="0" />
<file name="km.js" server="69.175.104.242//" local="132244608952885646" remote="132233482200000000" Dst="0" />
<file name="ko.js" server="69.175.104.242//" local="132244608954584672" remote="132233482200000000" Dst="0" />
<file name="lt.js" server="69.175.104.242//" local="132244608957033327" remote="132233482200000000" Dst="0" />
<file name="lv.js" server="69.175.104.242//" local="132244608957802883" remote="132233482200000000" Dst="0" />
<file name="mk.js" server="69.175.104.242//" local="132244608960196212" remote="132233482200000000" Dst="0" />
<file name="ms.js" server="69.175.104.242//" local="132244608961945207" remote="132233482200000000" Dst="0" />
<file name="nb.js" server="69.175.104.242//" local="132244608962904662" remote="132233482200000000" Dst="0" />
<file name="ne.js" server="69.175.104.242//" local="132244608964703711" remote="132233482200000000" Dst="0" />
<file name="nl.js" server="69.175.104.242//" local="132244608966582648" remote="132233482200000000" Dst="0" />
<file name="pl.js" server="69.175.104.242//" local="132244608967899262" remote="132233482200000000" Dst="0" />
<file name="ps.js" server="69.175.104.242//" local="132244608970038008" remote="132233482200000000" Dst="0" />
<file name="pt-BR.js" server="69.175.104.242//" local="132244608971896944" remote="132233482200000000" Dst="0" />
<file name="pt.js" server="69.175.104.242//" local="132244608972186789" remote="132233482200000000" Dst="0" />
<file name="ro.js" server="69.175.104.242//" local="132244608975235041" remote="132233482200000000" Dst="0" />
<file name="ru.js" server="69.175.104.242//" local="132244608977636638" remote="132233482200000000" Dst="0" />
<file name="sk.js" server="69.175.104.242//" local="132244608978556104" remote="132233482200000000" Dst="0" />
<file name="sl.js" server="69.175.104.242//" local="132244608980644916" remote="132233482200000000" Dst="0" />
<file name="sq.js" server="69.175.104.242//" local="132244608982543881" remote="132233482200000000" Dst="0" />
<file name="sr-Cyrl.js" server="69.175.104.242//" local="132244608983770868" remote="132233482200000000" Dst="0" />
<file name="sr.js" server="69.175.104.242//" local="132244608986139509" remote="132233482200000000" Dst="0" />
<file name="sv.js" server="69.175.104.242//" local="132244608987218891" remote="132233482200000000" Dst="0" />
<file name="th.js" server="69.175.104.242//" local="132244608989377658" remote="132233482200000000" Dst="0" />
<file name="tk.js" server="69.175.104.242//" local="132244608991596408" remote="132233482200000000" Dst="0" />
<file name="tr.js" server="69.175.104.242//" local="132244608992545853" remote="132233482200000000" Dst="0" />
<file name="uk.js" server="69.175.104.242//" local="132244608993395371" remote="132233482200000000" Dst="0" />
<file name="vi.js" server="69.175.104.242//" local="132244608996143836" remote="132233482200000000" Dst="0" />
<file name="zh-CN.js" server="69.175.104.242//" local="132244608996352567" remote="132233482200000000" Dst="0" />
<file name="zh-TW.js" server="69.175.104.242//" local="132244608997420996" remote="132233482200000000" Dst="0" />
<file name="af.js" server="alcaldialaunion.gob.sv//" local="132372423505134232" remote="132271503600000000" Dst="0" />
<file name="ar.js" server="alcaldialaunion.gob.sv//" local="132372423511060506" remote="132271503600000000" Dst="0" />
<file name="az.js" server="alcaldialaunion.gob.sv//" local="132372423511110479" remote="132271503600000000" Dst="0" />
<file name="bg.js" server="alcaldialaunion.gob.sv//" local="132372423512077859" remote="132271503600000000" Dst="0" />
<file name="bn.js" server="alcaldialaunion.gob.sv//" local="132372423516415613" remote="132271503600000000" Dst="0" />
<file name="bs.js" server="alcaldialaunion.gob.sv//" local="132372423516355604" remote="132271503600000000" Dst="0" />
<file name="build.txt" server="alcaldialaunion.gob.sv//" local="132372423516125778" remote="132271503600000000" Dst="0" />
<file name="ca.js" server="alcaldialaunion.gob.sv//" local="132372423520941702" remote="132271503600000000" Dst="0" />
<file name="cs.js" server="alcaldialaunion.gob.sv//" local="132372423520961741" remote="132271503600000000" Dst="0" />
<file name="da.js" server="alcaldialaunion.gob.sv//" local="132372423522770244" remote="132271503600000000" Dst="0" />
<file name="de.js" server="alcaldialaunion.gob.sv//" local="132372423527250948" remote="132271503600000000" Dst="0" />
<file name="dsb.js" server="alcaldialaunion.gob.sv//" local="132372423527200985" remote="132271503600000000" Dst="0" />
<file name="el.js" server="alcaldialaunion.gob.sv//" local="132372423527141079" remote="132271503600000000" Dst="0" />
<file name="en.js" server="alcaldialaunion.gob.sv//" local="132372423532889367" remote="132271503600000000" Dst="0" />
<file name="es.js" server="alcaldialaunion.gob.sv//" local="132372423532859412" remote="132271503600000000" Dst="0" />
<file name="et.js" server="alcaldialaunion.gob.sv//" local="132372423534572980" remote="132271503600000000" Dst="0" />
<file name="eu.js" server="alcaldialaunion.gob.sv//" local="132372423537269039" remote="132271503600000000" Dst="0" />
<file name="fa.js" server="alcaldialaunion.gob.sv//" local="132372423538970888" remote="132271503600000000" Dst="0" />
<file name="fi.js" server="alcaldialaunion.gob.sv//" local="132372423541227841" remote="132271503600000000" Dst="0" />
<file name="fr.js" server="alcaldialaunion.gob.sv//" local="132372423542789584" remote="132271503600000000" Dst="0" />
<file name="gl.js" server="alcaldialaunion.gob.sv//" local="132372423543965904" remote="132271503600000000" Dst="0" />
<file name="he.js" server="alcaldialaunion.gob.sv//" local="132372423545465232" remote="132271503600000000" Dst="0" />
<file name="hi.js" server="alcaldialaunion.gob.sv//" local="132372423547792522" remote="132271503600000000" Dst="0" />
<file name="hr.js" server="alcaldialaunion.gob.sv//" local="132372423548774513" remote="132271503600000000" Dst="0" />
<file name="hsb.js" server="alcaldialaunion.gob.sv//" local="132372423551566201" remote="132271503600000000" Dst="0" />
<file name="hu.js" server="alcaldialaunion.gob.sv//" local="132372423553729198" remote="132271503600000000" Dst="0" />
<file name="hy.js" server="alcaldialaunion.gob.sv//" local="132372423554897278" remote="132271503600000000" Dst="0" />
<file name="id.js" server="alcaldialaunion.gob.sv//" local="132372423558136233" remote="132271503600000000" Dst="0" />
<file name="is.js" server="alcaldialaunion.gob.sv//" local="132372423559901546" remote="132271503600000000" Dst="0" />
<file name="it.js" server="alcaldialaunion.gob.sv//" local="132372423559941451" remote="132271503600000000" Dst="0" />
<file name="ja.js" server="alcaldialaunion.gob.sv//" local="132372423563228727" remote="132271503600000000" Dst="0" />
<file name="km.js" server="alcaldialaunion.gob.sv//" local="132372423565369146" remote="132271503600000000" Dst="0" />
<file name="ka.js" server="alcaldialaunion.gob.sv//" local="132372423565309149" remote="132271503600000000" Dst="0" />
<file name="ko.js" server="alcaldialaunion.gob.sv//" local="132372423567461499" remote="132271503600000000" Dst="0" />
<file name="lt.js" server="alcaldialaunion.gob.sv//" local="132372423570312414" remote="132271503600000000" Dst="0" />
<file name="lv.js" server="alcaldialaunion.gob.sv//" local="132372423570262502" remote="132271503600000000" Dst="0" />
<file name="mk.js" server="alcaldialaunion.gob.sv//" local="132372423573833300" remote="132271503600000000" Dst="0" />
<file name="ms.js" server="alcaldialaunion.gob.sv//" local="132372423575432373" remote="132271503600000000" Dst="0" />
<file name="nb.js" server="alcaldialaunion.gob.sv//" local="132372423576651667" remote="132271503600000000" Dst="0" />
<file name="ne.js" server="alcaldialaunion.gob.sv//" local="132372423578870409" remote="132271503600000000" Dst="0" />
<file name="nl.js" server="alcaldialaunion.gob.sv//" local="132372423582044806" remote="132271503600000000" Dst="0" />
<file name="pl.js" server="alcaldialaunion.gob.sv//" local="132372423582761495" remote="132271503600000000" Dst="0" />
<file name="ps.js" server="alcaldialaunion.gob.sv//" local="132372423583843150" remote="132271503600000000" Dst="0" />
<file name="pt-BR.js" server="alcaldialaunion.gob.sv//" local="132372423587310349" remote="132271503600000000" Dst="0" />
<file name="pt.js" server="alcaldialaunion.gob.sv//" local="132372423587260202" remote="132271503600000000" Dst="0" />
<file name="ro.js" server="alcaldialaunion.gob.sv//" local="132372423589846382" remote="132271503600000000" Dst="0" />
<file name="ru.js" server="alcaldialaunion.gob.sv//" local="132372423591923483" remote="132271503600000000" Dst="0" />
<file name="sk.js" server="alcaldialaunion.gob.sv//" local="132372423591973411" remote="132271503600000000" Dst="0" />
<file name="sl.js" server="alcaldialaunion.gob.sv//" local="132372423593879738" remote="132271503600000000" Dst="0" />
<file name="sq.js" server="alcaldialaunion.gob.sv//" local="132372423598349158" remote="132271503600000000" Dst="0" />
<file name="sr-Cyrl.js" server="alcaldialaunion.gob.sv//" local="132372423598389053" remote="132271503600000000" Dst="0" />
<file name="sr.js" server="alcaldialaunion.gob.sv//" local="132372423599925586" remote="132271503600000000" Dst="0" />
<file name="sv.js" server="alcaldialaunion.gob.sv//" local="132372423605417172" remote="132271503600000000" Dst="0" />
<file name="th.js" server="alcaldialaunion.gob.sv//" local="132372423605486799" remote="132271503600000000" Dst="0" />
<file name="tk.js" server="alcaldialaunion.gob.sv//" local="132372423605556774" remote="132271503600000000" Dst="0" />
<file name="tr.js" server="alcaldialaunion.gob.sv//" local="132372423610163788" remote="132271503600000000" Dst="0" />
<file name="uk.js" server="alcaldialaunion.gob.sv//" local="132372423610273620" remote="132271503600000000" Dst="0" />
<file name="vi.js" server="alcaldialaunion.gob.sv//" local="132372423610388963" remote="132271503600000000" Dst="0" />
<file name="zh-CN.js" server="alcaldialaunion.gob.sv//" local="132372423613700918" remote="132271503600000000" Dst="0" />
<file name="zh-TW.js" server="alcaldialaunion.gob.sv//" local="132372423613808708" remote="132271503600000000" Dst="0" />
</dwsync>